{
  "annotations": {
    "list": [
      {
        "builtIn": 1,
        "datasource": {
          "type": "grafana",
          "uid": "-- Grafana --"
        },
        "enable": true,
        "hide": true,
        "iconColor": "rgba(0, 211, 255, 1)",
        "name": "Annotations & Alerts",
        "target": {
          "limit": 100,
          "matchAny": false,
          "tags": [],
          "type": "dashboard"
        },
        "type": "dashboard"
      }
    ]
  },
  "editable": true,
  "fiscalYearStartMonth": 0,
  "graphTooltip": 0,
  "links": [],
  "liveNow": false,
  "panels": [
    {
      "collapsed": false,
      "gridPos": {
        "h": 1,
        "w": 24,
        "x": 0,
        "y": 0
      },
      "id": 14,
      "panels": [],
      "title": "Quick Overview",
      "type": "row"
    },
    {
      "datasource": {
        "type": "prometheus",
        "uid": "P1809F7CD0C75ACF3"
      },
      "fieldConfig": {
        "defaults": {
          "color": {
            "mode": "thresholds"
          },
          "mappings": [
            {
              "options": {
                "0": {
                  "color": "red",
                  "index": 1,
                  "text": "DOWN"
                },
                "1": {
                  "color": "green",
                  "index": 0,
                  "text": "UP"
                }
              },
              "type": "value"
            }
          ],
          "thresholds": {
            "mode": "absolute",
            "steps": [
              {
                "color": "green",
                "value": null
              },
              {
                "color": "red",
                "value": 80
              }
            ]
          }
        },
        "overrides": []
      },
      "gridPos": {
        "h": 5,
        "w": 8,
        "x": 0,
        "y": 1
      },
      "id": 2,
      "options": {
        "colorMode": "value",
        "graphMode": "none",
        "justifyMode": "auto",
        "orientation": "auto",
        "reduceOptions": {
          "calcs": [
            "lastNotNull"
          ],
          "fields": "",
          "values": false
        },
        "textMode": "auto"
      },
      "pluginVersion": "9.2.4",
      "targets": [
        {
          "datasource": {
            "type": "prometheus",
            "uid": "P1809F7CD0C75ACF3"
          },
          "editorMode": "code",
          "expr": "up{job=\"system-monitor\"}",
          "legendFormat": "__auto",
          "range": true,
          "refId": "A"
        }
      ],
      "title": "System monitor health check",
      "transformations": [
        {
          "id": "convertFieldType",
          "options": {
            "conversions": [
              {}
            ],
            "fields": {}
          }
        }
      ],
      "type": "stat"
    },
    {
      "datasource": {
        "type": "prometheus",
        "uid": "P1809F7CD0C75ACF3"
      },
      "fieldConfig": {
        "defaults": {
          "color": {
            "mode": "thresholds"
          },
          "mappings": [
            {
              "options": {
                "0": {
                  "color": "red",
                  "index": 1,
                  "text": "DOWN"
                },
                "1": {
                  "color": "green",
                  "index": 0,
                  "text": "UP"
                }
              },
              "type": "value"
            }
          ],
          "thresholds": {
            "mode": "absolute",
            "steps": [
              {
                "color": "green",
                "value": null
              },
              {
                "color": "red",
                "value": 80
              }
            ]
          }
        },
        "overrides": []
      },
      "gridPos": {
        "h": 5,
        "w": 8,
        "x": 8,
        "y": 1
      },
      "id": 3,
      "options": {
        "colorMode": "value",
        "graphMode": "none",
        "justifyMode": "auto",
        "orientation": "auto",
        "reduceOptions": {
          "calcs": [
            "lastNotNull"
          ],
          "fields": "",
          "values": false
        },
        "textMode": "auto"
      },
      "pluginVersion": "9.2.4",
      "targets": [
        {
          "datasource": {
            "type": "prometheus",
            "uid": "P1809F7CD0C75ACF3"
          },
          "editorMode": "code",
          "expr": "up{job=\"prometheus\"}",
          "legendFormat": "__auto",
          "range": true,
          "refId": "A"
        }
      ],
      "title": "Prometheus health check",
      "transformations": [
        {
          "id": "convertFieldType",
          "options": {
            "conversions": [
              {}
            ],
            "fields": {}
          }
        }
      ],
      "type": "stat"
    },
    {
      "datasource": {
        "type": "prometheus",
        "uid": "P1809F7CD0C75ACF3"
      },
      "fieldConfig": {
        "defaults": {
          "color": {
            "mode": "thresholds"
          },
          "mappings": [
            {
              "options": {
                "0": {
                  "color": "red",
                  "index": 1,
                  "text": "DOWN"
                },
                "1": {
                  "color": "green",
                  "index": 0,
                  "text": "UP"
                }
              },
              "type": "value"
            }
          ],
          "thresholds": {
            "mode": "absolute",
            "steps": [
              {
                "color": "green",
                "value": null
              },
              {
                "color": "red",
                "value": 80
              }
            ]
          }
        },
        "overrides": []
      },
      "gridPos": {
        "h": 5,
        "w": 8,
        "x": 16,
        "y": 1
      },
      "id": 4,
      "options": {
        "colorMode": "value",
        "graphMode": "none",
        "justifyMode": "auto",
        "orientation": "auto",
        "reduceOptions": {
          "calcs": [
            "lastNotNull"
          ],
          "fields": "",
          "values": false
        },
        "textMode": "auto"
      },
      "pluginVersion": "9.2.4",
      "targets": [
        {
          "datasource": {
            "type": "prometheus",
            "uid": "P1809F7CD0C75ACF3"
          },
          "editorMode": "code",
          "expr": "up{job=\"prometheus-alertmanager\"}",
          "legendFormat": "__auto",
          "range": true,
          "refId": "A"
        }
      ],
      "title": "Alert manager health check",
      "transformations": [
        {
          "id": "convertFieldType",
          "options": {
            "conversions": [
              {}
            ],
            "fields": {}
          }
        }
      ],
      "type": "stat"
    },
    {
      "datasource": {
        "type": "prometheus",
        "uid": "P1809F7CD0C75ACF3"
      },
      "fieldConfig": {
        "defaults": {
          "color": {
            "mode": "thresholds"
          },
          "mappings": [
            {
              "options": {
                "from": 0,
                "result": {
                  "color": "green",
                  "index": 0,
                  "text": "UP"
                },
                "to": 60
              },
              "type": "range"
            },
            {
              "options": {
                "from": 61,
                "result": {
                  "color": "red",
                  "index": 1,
                  "text": "DOWN"
                },
                "to": 9999999
              },
              "type": "range"
            }
          ],
          "thresholds": {
            "mode": "absolute",
            "steps": [
              {
                "color": "green",
                "value": null
              },
              {
                "color": "red",
                "value": 80
              }
            ]
          }
        },
        "overrides": []
      },
      "gridPos": {
        "h": 6,
        "w": 24,
        "x": 0,
        "y": 6
      },
      "id": 10,
      "options": {
        "colorMode": "value",
        "graphMode": "none",
        "justifyMode": "auto",
        "orientation": "auto",
        "reduceOptions": {
          "calcs": [
            "lastNotNull"
          ],
          "fields": "",
          "values": false
        },
        "textMode": "auto"
      },
      "pluginVersion": "9.2.4",
      "targets": [
        {
          "datasource": {
            "type": "prometheus",
            "uid": "P1809F7CD0C75ACF3"
          },
          "editorMode": "code",
          "expr": "time() - monitoring_collector_up_timestamp_seconds",
          "legendFormat": "{{source}}",
          "range": true,
          "refId": "A"
        }
      ],
      "title": "Docker metrics collectors health check",
      "transformations": [
        {
          "id": "convertFieldType",
          "options": {
            "conversions": [
              {}
            ],
            "fields": {}
          }
        }
      ],
      "type": "stat"
    },
    {
      "datasource": {
        "type": "prometheus",
        "uid": "P1809F7CD0C75ACF3"
      },
      "fieldConfig": {
        "defaults": {
          "color": {
            "mode": "thresholds"
          },
          "decimals": 0,
          "mappings": [],
          "thresholds": {
            "mode": "absolute",
            "steps": [
              {
                "color": "green",
                "value": null
              },
              {
                "color": "red",
                "value": 1
              }
            ]
          }
        },
        "overrides": []
      },
      "gridPos": {
        "h": 6,
        "w": 12,
        "x": 0,
        "y": 12
      },
      "id": 17,
      "options": {
        "colorMode": "value",
        "graphMode": "none",
        "justifyMode": "auto",
        "orientation": "auto",
        "reduceOptions": {
          "calcs": [
            "last"
          ],
          "fields": "",
          "values": false
        },
        "textMode": "auto"
      },
      "pluginVersion": "9.2.4",
      "targets": [
        {
          "datasource": {
            "type": "prometheus",
            "uid": "P1809F7CD0C75ACF3"
          },
          "editorMode": "code",
          "exemplar": false,
          "expr": "sum(increase(monitoring_alerts_total{status=\"firing\"}[60m]))",
          "instant": true,
          "legendFormat": "__auto",
          "range": false,
          "refId": "A"
        }
      ],
      "title": "Alerts in the last hour",
      "type": "stat"
    },
    {
      "datasource": {
        "type": "prometheus",
        "uid": "P1809F7CD0C75ACF3"
      },
      "fieldConfig": {
        "defaults": {
          "color": {
            "mode": "thresholds"
          },
          "decimals": 0,
          "mappings": [],
          "thresholds": {
            "mode": "absolute",
            "steps": [
              {
                "color": "green",
                "value": null
              },
              {
                "color": "red",
                "value": 1
              }
            ]
          }
        },
        "overrides": []
      },
      "gridPos": {
        "h": 6,
        "w": 12,
        "x": 12,
        "y": 12
      },
      "id": 12,
      "maxDataPoints": 1,
      "options": {
        "colorMode": "value",
        "graphMode": "none",
        "justifyMode": "auto",
        "orientation": "auto",
        "reduceOptions": {
          "calcs": [
            "last"
          ],
          "fields": "",
          "values": false
        },
        "textMode": "auto"
      },
      "pluginVersion": "9.2.4",
      "targets": [
        {
          "datasource": {
            "type": "prometheus",
            "uid": "P1809F7CD0C75ACF3"
          },
          "editorMode": "code",
          "exemplar": false,
          "expr": "sum(increase(monitoring_alerts_total{status=\"firing\"}[24h]))",
          "instant": true,
          "legendFormat": "__auto",
          "range": false,
          "refId": "A"
        }
      ],
      "title": "Alerts in the last 24h",
      "type": "stat"
    },
    {
      "collapsed": false,
      "gridPos": {
        "h": 1,
        "w": 24,
        "x": 0,
        "y": 18
      },
      "id": 16,
      "panels": [],
      "title": "Details",
      "type": "row"
    },
    {
      "datasource": {
        "type": "prometheus",
        "uid": "P1809F7CD0C75ACF3"
      },
      "description": "Count of new alerts, appearing in the 15 minutes time window",
      "fieldConfig": {
        "defaults": {
          "color": {
            "mode": "palette-classic"
          },
          "custom": {
            "axisCenteredZero": false,
            "axisColorMode": "text",
            "axisLabel": "",
            "axisPlacement": "auto",
            "barAlignment": 0,
            "drawStyle": "line",
            "fillOpacity": 0,
            "gradientMode": "none",
            "hideFrom": {
              "legend": false,
              "tooltip": false,
              "viz": false
            },
            "lineInterpolation": "linear",
            "lineWidth": 1,
            "pointSize": 5,
            "scaleDistribution": {
              "type": "linear"
            },
            "showPoints": "auto",
            "spanNulls": false,
            "stacking": {
              "group": "A",
              "mode": "none"
            },
            "thresholdsStyle": {
              "mode": "off"
            }
          },
          "decimals": 0,
          "mappings": [
            {
              "options": {
                "firing": {
                  "color": "red",
                  "index": 0
                }
              },
              "type": "value"
            }
          ],
          "min": 0,
          "thresholds": {
            "mode": "absolute",
            "steps": [
              {
                "color": "green",
                "value": null
              }
            ]
          }
        },
        "overrides": [
          {
            "matcher": {
              "id": "byName",
              "options": "resolved"
            },
            "properties": [
              {
                "id": "color",
                "value": {
                  "fixedColor": "green",
                  "mode": "fixed"
                }
              }
            ]
          },
          {
            "matcher": {
              "id": "byName",
              "options": "firing"
            },
            "properties": [
              {
                "id": "color",
                "value": {
                  "fixedColor": "red",
                  "mode": "fixed"
                }
              }
            ]
          }
        ]
      },
      "gridPos": {
        "h": 8,
        "w": 24,
        "x": 0,
        "y": 19
      },
      "id": 6,
      "interval": "5m",
      "options": {
        "legend": {
          "calcs": [],
          "displayMode": "list",
          "placement": "bottom",
          "showLegend": true
        },
        "tooltip": {
          "mode": "single",
          "sort": "none"
        }
      },
      "targets": [
        {
          "datasource": {
            "type": "prometheus",
            "uid": "P1809F7CD0C75ACF3"
          },
          "editorMode": "code",
          "expr": "sum by (status) (increase(monitoring_alerts_total[15m]))",
          "legendFormat": "{{label_alertname}}",
          "range": true,
          "refId": "A"
        }
      ],
      "title": "New alerts in time",
      "type": "timeseries"
    },
    {
      "datasource": {
        "type": "prometheus",
        "uid": "P1809F7CD0C75ACF3"
      },
      "fieldConfig": {
        "defaults": {
          "color": {
            "mode": "thresholds"
          },
          "custom": {
            "align": "auto",
            "displayMode": "auto",
            "inspect": false
          },
          "mappings": [],
          "thresholds": {
            "mode": "absolute",
            "steps": [
              {
                "color": "green",
                "value": null
              },
              {
                "color": "red",
                "value": 80
              }
            ]
          }
        },
        "overrides": []
      },
      "gridPos": {
        "h": 10,
        "w": 24,
        "x": 0,
        "y": 27
      },
      "id": 8,
      "interval": "15m",
      "options": {
        "footer": {
          "fields": "",
          "reducer": [
            "sum"
          ],
          "show": false
        },
        "frameIndex": 0,
        "showHeader": true
      },
      "pluginVersion": "9.2.4",
      "targets": [
        {
          "datasource": {
            "type": "prometheus",
            "uid": "P1809F7CD0C75ACF3"
          },
          "editorMode": "code",
          "expr": "increase(monitoring_alerts_total{status=\"firing\"}[30m]) > 0",
          "legendFormat": "__auto",
          "range": true,
          "refId": "A"
        }
      ],
      "title": "New alerts details",
      "transformations": [
        {
          "id": "labelsToFields",
          "options": {
            "keepLabels": [
              "annotation_summary",
              "instance",
              "job",
              "label_alertname",
              "label_instance",
              "label_job",
              "label_severity",
              "label_application",
              "label_instance_id",
              "label_source"
            ],
            "mode": "columns"
          }
        },
        {
          "id": "sortBy",
          "options": {
            "fields": {},
            "sort": [
              {
                "desc": true,
                "field": "Time"
              }
            ]
          }
        }
      ],
      "type": "table"
    }
  ],
  "refresh": "1m",
  "schemaVersion": 37,
  "style": "dark",
  "tags": [],
  "templating": {
    "list": []
  },
  "time": {
    "from": "now-24h",
    "to": "now"
  },
  "timepicker": {},
  "timezone": "",
  "title": "Alerts",
  "uid": "alerts",
  "version": 1,
  "weekStart": ""
}